README.txt
setup.cfg
setup.py
plone/__init__.py
plone.app.gloworm.egg-info/PKG-INFO
plone.app.gloworm.egg-info/SOURCES.txt
plone.app.gloworm.egg-info/dependency_links.txt
plone.app.gloworm.egg-info/entry_points.txt
plone.app.gloworm.egg-info/namespace_packages.txt
plone.app.gloworm.egg-info/not-zip-safe
plone.app.gloworm.egg-info/paster_plugins.txt
plone.app.gloworm.egg-info/requires.txt
plone.app.gloworm.egg-info/top_level.txt
plone/app/__init__.py
plone/app/gloworm/__init__.py
plone/app/gloworm/configure.zcml
plone/app/gloworm/tests.py