Metadata-Version: 1.0
Name: plone.app.gloworm
Version: 0.1a10
Summary: UNKNOWN
Home-page: https://weblion.psu.edu/svn/weblion/weblion/Products.Gloworm/
Author: WebLion Group, Penn State University
Author-email: support@weblion.psu.edu
License: GPL
Platform: UNKNOWN
Classifier: Framework :: Plone
Classifier: Programming Language :: Python
Classifier: Topic :: Software Development :: Libraries :: Python Modules
